projects/__init__.py
pytorch3d/_C.cpython-38-darwin.so
pytorch3d/__init__.py
pytorch3d/common/__init__.py
pytorch3d/common/compat.py
pytorch3d/common/datatypes.py
pytorch3d/common/linear_with_repeat.py
pytorch3d/common/workaround/__init__.py
pytorch3d/common/workaround/symeig3x3.py
pytorch3d/common/workaround/utils.py
pytorch3d/datasets/__init__.py
pytorch3d/datasets/shapenet_base.py
pytorch3d/datasets/utils.py
pytorch3d/datasets/r2n2/__init__.py
pytorch3d/datasets/r2n2/r2n2.py
pytorch3d/datasets/r2n2/r2n2_synset_dict.json
pytorch3d/datasets/r2n2/utils.py
pytorch3d/datasets/shapenet/__init__.py
pytorch3d/datasets/shapenet/shapenet_core.py
pytorch3d/datasets/shapenet/shapenet_synset_dict_v1.json
pytorch3d/datasets/shapenet/shapenet_synset_dict_v2.json
pytorch3d/implicitron/__init__.py
pytorch3d/implicitron/eval_demo.py
pytorch3d/implicitron/dataset/__init__.py
pytorch3d/implicitron/dataset/blender_dataset_map_provider.py
pytorch3d/implicitron/dataset/data_loader_map_provider.py
pytorch3d/implicitron/dataset/data_source.py
pytorch3d/implicitron/dataset/dataset_base.py
pytorch3d/implicitron/dataset/dataset_map_provider.py
pytorch3d/implicitron/dataset/frame_data.py
pytorch3d/implicitron/dataset/json_index_dataset.py
pytorch3d/implicitron/dataset/json_index_dataset_map_provider.py
pytorch3d/implicitron/dataset/json_index_dataset_map_provider_v2.py
pytorch3d/implicitron/dataset/llff_dataset_map_provider.py
pytorch3d/implicitron/dataset/load_blender.py
pytorch3d/implicitron/dataset/load_llff.py
pytorch3d/implicitron/dataset/orm_types.py
pytorch3d/implicitron/dataset/rendered_mesh_dataset_map_provider.py
pytorch3d/implicitron/dataset/scene_batch_sampler.py
pytorch3d/implicitron/dataset/single_sequence_dataset.py
pytorch3d/implicitron/dataset/sql_dataset.py
pytorch3d/implicitron/dataset/sql_dataset_provider.py
pytorch3d/implicitron/dataset/train_eval_data_loader_provider.py
pytorch3d/implicitron/dataset/types.py
pytorch3d/implicitron/dataset/utils.py
pytorch3d-0.7.4.dist-info/LICENSE
pytorch3d-0.7.4.dist-info/LICENSE-3RD-PARTY
pytorch3d-0.7.4.dist-info/METADATA
pytorch3d-0.7.4.dist-info/WHEEL
pytorch3d-0.7.4.dist-info/entry_points.txt
pytorch3d-0.7.4.dist-info/top_level.txt
pytorch3d-0.7.4.dist-info/RECORD
